[
    {
        "code": "KS/W76-E001",
        "name": "",
        "rarity": "",
        "bushi": "https://en.ws-tcg.com/cardlist/list/?cardno=KS/W76-E001"
    },
    {
        "code": "KS/W76-E002",
        "name": "",
        "rarity": "",
        "bushi": "https://en.ws-tcg.com/cardlist/list/?cardno=KS/W76-E002"
    },
    {
        "code": "KS/W76-E003",
        "name": "",
        "rarity": "",
        "bushi": "https://en.ws-tcg.com/cardlist/list/?cardno=KS/W76-E003"
    },
    {
        "code": "KS/W76-E004",
        "name": "",
        "rarity": "",
        "bushi": "https://en.ws-tcg.com/cardlist/list/?cardno=KS/W76-E004"
    },
    {
        "code": "KS/W76-E005",
        "name": "",
        "rarity": "",
        "bushi": "https://en.ws-tcg.com/cardlist/list/?cardno=KS/W76-E005"
    },
    {
        "code": "KS/W76-E006",
        "name": "",
        "rarity": "",
        "bushi": "https://en.ws-tcg.com/cardlist/list/?cardno=KS/W76-E006"
    },
    {
        "code": "KS/W76-E007",
        "name": "",
        "rarity": "",
        "bushi": "https://en.ws-tcg.com/cardlist/list/?cardno=KS/W76-E007"
    },
    {
        "code": "KS/W76-E008",
        "name": "",
        "rarity": "",
        "bushi": "https://en.ws-tcg.com/cardlist/list/?cardno=KS/W76-E008"
    },
    {
        "code": "KS/W76-E009",
        "name": "",
        "rarity": "",
        "bushi": "https://en.ws-tcg.com/cardlist/list/?cardno=KS/W76-E009"
    },
    {
        "code": "KS/W76-E010",
        "name": "",
        "rarity": "",
        "bushi": "https://en.ws-tcg.com/cardlist/list/?cardno=KS/W76-E010"
    },
    {
        "code": "KS/W76-E011",
        "name": "",
        "rarity": "",
        "bushi": "https://en.ws-tcg.com/cardlist/list/?cardno=KS/W76-E011"
    },
    {
        "code": "KS/W76-E012",
        "name": "",
        "rarity": "",
        "bushi": "https://en.ws-tcg.com/cardlist/list/?cardno=KS/W76-E012"
    },
    {
        "code": "KS/W76-E013",
        "name": "",
        "rarity": "",
        "bushi": "https://en.ws-tcg.com/cardlist/list/?cardno=KS/W76-E013"
    },
    {
        "code": "KS/W76-E014",
        "name": "",
        "rarity": "",
        "bushi": "https://en.ws-tcg.com/cardlist/list/?cardno=KS/W76-E014"
    },
    {
        "code": "KS/W76-E015",
        "name": "",
        "rarity": "",
        "bushi": "https://en.ws-tcg.com/cardlist/list/?cardno=KS/W76-E015"
    },
    {
        "code": "KS/W76-E016",
        "name": "",
        "rarity": "",
        "bushi": "https://en.ws-tcg.com/cardlist/list/?cardno=KS/W76-E016"
    },
    {
        "code": "KS/W76-E017",
        "name": "",
        "rarity": "",
        "bushi": "https://en.ws-tcg.com/cardlist/list/?cardno=KS/W76-E017"
    },
    {
        "code": "KS/W76-E018",
        "name": "",
        "rarity": "",
        "bushi": "https://en.ws-tcg.com/cardlist/list/?cardno=KS/W76-E018"
    },
    {
        "code": "KS/W76-E019",
        "name": "",
        "rarity": "",
        "bushi": "https://en.ws-tcg.com/cardlist/list/?cardno=KS/W76-E019"
    },
    {
        "code": "KS/W76-E020",
        "name": "",
        "rarity": "",
        "bushi": "https://en.ws-tcg.com/cardlist/list/?cardno=KS/W76-E020"
    },
    {
        "code": "KS/W76-E021",
        "name": "",
        "rarity": "",
        "bushi": "https://en.ws-tcg.com/cardlist/list/?cardno=KS/W76-E021"
    },
    {
        "code": "KS/W76-E022",
        "name": "",
        "rarity": "",
        "bushi": "https://en.ws-tcg.com/cardlist/list/?cardno=KS/W76-E022"
    },
    {
        "code": "KS/W76-E023",
        "name": "",
        "rarity": "",
        "bushi": "https://en.ws-tcg.com/cardlist/list/?cardno=KS/W76-E023"
    },
    {
        "code": "KS/W76-E024",
        "name": "",
        "rarity": "",
        "bushi": "https://en.ws-tcg.com/cardlist/list/?cardno=KS/W76-E024"
    },
    {
        "code": "KS/W76-E025",
        "name": "",
        "rarity": "",
        "bushi": "https://en.ws-tcg.com/cardlist/list/?cardno=KS/W76-E025"
    },
    {
        "code": "KS/W76-E026",
        "name": "",
        "rarity": "",
        "bushi": "https://en.ws-tcg.com/cardlist/list/?cardno=KS/W76-E026"
    },
    {
        "code": "KS/W76-E027",
        "name": "",
        "rarity": "",
        "bushi": "https://en.ws-tcg.com/cardlist/list/?cardno=KS/W76-E027"
    },
    {
        "code": "KS/W76-E028",
        "name": "",
        "rarity": "",
        "bushi": "https://en.ws-tcg.com/cardlist/list/?cardno=KS/W76-E028"
    },
    {
        "code": "KS/W76-E029",
        "name": "",
        "rarity": "",
        "bushi": "https://en.ws-tcg.com/cardlist/list/?cardno=KS/W76-E029"
    },
    {
        "code": "KS/W76-E030",
        "name": "",
        "rarity": "",
        "bushi": "https://en.ws-tcg.com/cardlist/list/?cardno=KS/W76-E030"
    },
    {
        "code": "KS/W76-E031",
        "name": "",
        "rarity": "",
        "bushi": "https://en.ws-tcg.com/cardlist/list/?cardno=KS/W76-E031"
    },
    {
        "code": "KS/W76-E032",
        "name": "",
        "rarity": "",
        "bushi": "https://en.ws-tcg.com/cardlist/list/?cardno=KS/W76-E032"
    },
    {
        "code": "KS/W76-E033",
        "name": "",
        "rarity": "",
        "bushi": "https://en.ws-tcg.com/cardlist/list/?cardno=KS/W76-E033"
    },
    {
        "code": "KS/W76-E034",
        "name": "",
        "rarity": "",
        "bushi": "https://en.ws-tcg.com/cardlist/list/?cardno=KS/W76-E034"
    },
    {
        "code": "KS/W76-E035",
        "name": "",
        "rarity": "",
        "bushi": "https://en.ws-tcg.com/cardlist/list/?cardno=KS/W76-E035"
    },
    {
        "code": "KS/W76-E036",
        "name": "",
        "rarity": "",
        "bushi": "https://en.ws-tcg.com/cardlist/list/?cardno=KS/W76-E036"
    },
    {
        "code": "KS/W76-E037",
        "name": "",
        "rarity": "",
        "bushi": "https://en.ws-tcg.com/cardlist/list/?cardno=KS/W76-E037"
    },
    {
        "code": "KS/W76-E038",
        "name": "",
        "rarity": "",
        "bushi": "https://en.ws-tcg.com/cardlist/list/?cardno=KS/W76-E038"
    },
    {
        "code": "KS/W76-E039",
        "name": "",
        "rarity": "",
        "bushi": "https://en.ws-tcg.com/cardlist/list/?cardno=KS/W76-E039"
    },
    {
        "code": "KS/W76-E040",
        "name": "",
        "rarity": "",
        "bushi": "https://en.ws-tcg.com/cardlist/list/?cardno=KS/W76-E040"
    },
    {
        "code": "KS/W76-E041",
        "name": "",
        "rarity": "",
        "bushi": "https://en.ws-tcg.com/cardlist/list/?cardno=KS/W76-E041"
    },
    {
        "code": "KS/W76-E042",
        "name": "",
        "rarity": "",
        "bushi": "https://en.ws-tcg.com/cardlist/list/?cardno=KS/W76-E042"
    },
    {
        "code": "KS/W76-E043",
        "name": "",
        "rarity": "",
        "bushi": "https://en.ws-tcg.com/cardlist/list/?cardno=KS/W76-E043"
    },
    {
        "code": "KS/W76-E044",
        "name": "",
        "rarity": "",
        "bushi": "https://en.ws-tcg.com/cardlist/list/?cardno=KS/W76-E044"
    },
    {
        "code": "KS/W76-E045",
        "name": "",
        "rarity": "",
        "bushi": "https://en.ws-tcg.com/cardlist/list/?cardno=KS/W76-E045"
    },
    {
        "code": "KS/W76-E046",
        "name": "",
        "rarity": "",
        "bushi": "https://en.ws-tcg.com/cardlist/list/?cardno=KS/W76-E046"
    },
    {
        "code": "KS/W76-E047a",
        "name": "",
        "rarity": "",
        "bushi": "https://en.ws-tcg.com/cardlist/list/?cardno=KS/W76-E047a"
    },
    {
        "code": "KS/W76-E048",
        "name": "",
        "rarity": "",
        "bushi": "https://en.ws-tcg.com/cardlist/list/?cardno=KS/W76-E048"
    },
    {
        "code": "KS/W76-E049",
        "name": "",
        "rarity": "",
        "bushi": "https://en.ws-tcg.com/cardlist/list/?cardno=KS/W76-E049"
    },
    {
        "code": "KS/W76-E050",
        "name": "",
        "rarity": "",
        "bushi": "https://en.ws-tcg.com/cardlist/list/?cardno=KS/W76-E050"
    },
    {
        "code": "KS/W76-E051",
        "name": "",
        "rarity": "",
        "bushi": "https://en.ws-tcg.com/cardlist/list/?cardno=KS/W76-E051"
    },
    {
        "code": "KS/W76-E052",
        "name": "",
        "rarity": "",
        "bushi": "https://en.ws-tcg.com/cardlist/list/?cardno=KS/W76-E052"
    },
    {
        "code": "KS/W76-E053",
        "name": "",
        "rarity": "",
        "bushi": "https://en.ws-tcg.com/cardlist/list/?cardno=KS/W76-E053"
    },
    {
        "code": "KS/W76-E054",
        "name": "",
        "rarity": "",
        "bushi": "https://en.ws-tcg.com/cardlist/list/?cardno=KS/W76-E054"
    },
    {
        "code": "KS/W76-E055",
        "name": "",
        "rarity": "",
        "bushi": "https://en.ws-tcg.com/cardlist/list/?cardno=KS/W76-E055"
    },
    {
        "code": "KS/W76-E056",
        "name": "",
        "rarity": "",
        "bushi": "https://en.ws-tcg.com/cardlist/list/?cardno=KS/W76-E056"
    },
    {
        "code": "KS/W76-E057",
        "name": "",
        "rarity": "",
        "bushi": "https://en.ws-tcg.com/cardlist/list/?cardno=KS/W76-E057"
    },
    {
        "code": "KS/W76-E058",
        "name": "",
        "rarity": "",
        "bushi": "https://en.ws-tcg.com/cardlist/list/?cardno=KS/W76-E058"
    },
    {
        "code": "KS/W76-E059",
        "name": "",
        "rarity": "",
        "bushi": "https://en.ws-tcg.com/cardlist/list/?cardno=KS/W76-E059"
    },
    {
        "code": "KS/W76-E060",
        "name": "",
        "rarity": "",
        "bushi": "https://en.ws-tcg.com/cardlist/list/?cardno=KS/W76-E060"
    },
    {
        "code": "KS/W76-E061",
        "name": "",
        "rarity": "",
        "bushi": "https://en.ws-tcg.com/cardlist/list/?cardno=KS/W76-E061"
    },
    {
        "code": "KS/W76-E062",
        "name": "",
        "rarity": "",
        "bushi": "https://en.ws-tcg.com/cardlist/list/?cardno=KS/W76-E062"
    },
    {
        "code": "KS/W76-E063",
        "name": "",
        "rarity": "",
        "bushi": "https://en.ws-tcg.com/cardlist/list/?cardno=KS/W76-E063"
    },
    {
        "code": "KS/W76-E064",
        "name": "",
        "rarity": "",
        "bushi": "https://en.ws-tcg.com/cardlist/list/?cardno=KS/W76-E064"
    },
    {
        "code": "KS/W76-E065",
        "name": "",
        "rarity": "",
        "bushi": "https://en.ws-tcg.com/cardlist/list/?cardno=KS/W76-E065"
    },
    {
        "code": "KS/W76-E066",
        "name": "",
        "rarity": "",
        "bushi": "https://en.ws-tcg.com/cardlist/list/?cardno=KS/W76-E066"
    },
    {
        "code": "KS/W76-E067",
        "name": "",
        "rarity": "",
        "bushi": "https://en.ws-tcg.com/cardlist/list/?cardno=KS/W76-E067"
    },
    {
        "code": "KS/W76-E068",
        "name": "",
        "rarity": "",
        "bushi": "https://en.ws-tcg.com/cardlist/list/?cardno=KS/W76-E068"
    },
    {
        "code": "KS/W76-E069",
        "name": "",
        "rarity": "",
        "bushi": "https://en.ws-tcg.com/cardlist/list/?cardno=KS/W76-E069"
    },
    {
        "code": "KS/W76-E070",
        "name": "",
        "rarity": "",
        "bushi": "https://en.ws-tcg.com/cardlist/list/?cardno=KS/W76-E070"
    },
    {
        "code": "KS/W76-E071",
        "name": "",
        "rarity": "",
        "bushi": "https://en.ws-tcg.com/cardlist/list/?cardno=KS/W76-E071"
    },
    {
        "code": "KS/W76-E072",
        "name": "",
        "rarity": "",
        "bushi": "https://en.ws-tcg.com/cardlist/list/?cardno=KS/W76-E072"
    },
    {
        "code": "KS/W76-E073",
        "name": "",
        "rarity": "",
        "bushi": "https://en.ws-tcg.com/cardlist/list/?cardno=KS/W76-E073"
    },
    {
        "code": "KS/W76-E074",
        "name": "",
        "rarity": "",
        "bushi": "https://en.ws-tcg.com/cardlist/list/?cardno=KS/W76-E074"
    },
    {
        "code": "KS/W76-E075",
        "name": "",
        "rarity": "",
        "bushi": "https://en.ws-tcg.com/cardlist/list/?cardno=KS/W76-E075"
    },
    {
        "code": "KS/W76-E076",
        "name": "",
        "rarity": "",
        "bushi": "https://en.ws-tcg.com/cardlist/list/?cardno=KS/W76-E076"
    },
    {
        "code": "KS/W76-E077",
        "name": "",
        "rarity": "",
        "bushi": "https://en.ws-tcg.com/cardlist/list/?cardno=KS/W76-E077"
    },
    {
        "code": "KS/W76-E078",
        "name": "",
        "rarity": "",
        "bushi": "https://en.ws-tcg.com/cardlist/list/?cardno=KS/W76-E078"
    },
    {
        "code": "KS/W76-E079",
        "name": "",
        "rarity": "",
        "bushi": "https://en.ws-tcg.com/cardlist/list/?cardno=KS/W76-E079"
    },
    {
        "code": "KS/W76-E080",
        "name": "",
        "rarity": "",
        "bushi": "https://en.ws-tcg.com/cardlist/list/?cardno=KS/W76-E080"
    },
    {
        "code": "KS/W76-E081",
        "name": "",
        "rarity": "",
        "bushi": "https://en.ws-tcg.com/cardlist/list/?cardno=KS/W76-E081"
    },
    {
        "code": "KS/W76-E082",
        "name": "",
        "rarity": "",
        "bushi": "https://en.ws-tcg.com/cardlist/list/?cardno=KS/W76-E082"
    },
    {
        "code": "KS/W76-E083",
        "name": "",
        "rarity": "",
        "bushi": "https://en.ws-tcg.com/cardlist/list/?cardno=KS/W76-E083"
    },
    {
        "code": "KS/W76-E084",
        "name": "",
        "rarity": "",
        "bushi": "https://en.ws-tcg.com/cardlist/list/?cardno=KS/W76-E084"
    },
    {
        "code": "KS/W76-E085",
        "name": "",
        "rarity": "",
        "bushi": "https://en.ws-tcg.com/cardlist/list/?cardno=KS/W76-E085"
    },
    {
        "code": "KS/W76-E086",
        "name": "",
        "rarity": "",
        "bushi": "https://en.ws-tcg.com/cardlist/list/?cardno=KS/W76-E086"
    },
    {
        "code": "KS/W76-E087",
        "name": "",
        "rarity": "",
        "bushi": "https://en.ws-tcg.com/cardlist/list/?cardno=KS/W76-E087"
    },
    {
        "code": "KS/W76-E088",
        "name": "",
        "rarity": "",
        "bushi": "https://en.ws-tcg.com/cardlist/list/?cardno=KS/W76-E088"
    },
    {
        "code": "KS/W76-E089",
        "name": "",
        "rarity": "",
        "bushi": "https://en.ws-tcg.com/cardlist/list/?cardno=KS/W76-E089"
    },
    {
        "code": "KS/W76-E090",
        "name": "",
        "rarity": "",
        "bushi": "https://en.ws-tcg.com/cardlist/list/?cardno=KS/W76-E090"
    },
    {
        "code": "KS/W76-E091",
        "name": "",
        "rarity": "",
        "bushi": "https://en.ws-tcg.com/cardlist/list/?cardno=KS/W76-E091"
    },
    {
        "code": "KS/W76-E092",
        "name": "",
        "rarity": "",
        "bushi": "https://en.ws-tcg.com/cardlist/list/?cardno=KS/W76-E092"
    },
    {
        "code": "KS/W76-E093",
        "name": "",
        "rarity": "",
        "bushi": "https://en.ws-tcg.com/cardlist/list/?cardno=KS/W76-E093"
    },
    {
        "code": "KS/W76-E094",
        "name": "",
        "rarity": "",
        "bushi": "https://en.ws-tcg.com/cardlist/list/?cardno=KS/W76-E094"
    },
    {
        "code": "KS/W76-E095",
        "name": "",
        "rarity": "",
        "bushi": "https://en.ws-tcg.com/cardlist/list/?cardno=KS/W76-E095"
    },
    {
        "code": "KS/W76-E096",
        "name": "",
        "rarity": "",
        "bushi": "https://en.ws-tcg.com/cardlist/list/?cardno=KS/W76-E096"
    },
    {
        "code": "KS/W76-E097",
        "name": "",
        "rarity": "",
        "bushi": "https://en.ws-tcg.com/cardlist/list/?cardno=KS/W76-E097"
    },
    {
        "code": "KS/W76-E098",
        "name": "",
        "rarity": "",
        "bushi": "https://en.ws-tcg.com/cardlist/list/?cardno=KS/W76-E098"
    },
    {
        "code": "KS/W76-E099",
        "name": "",
        "rarity": "",
        "bushi": "https://en.ws-tcg.com/cardlist/list/?cardno=KS/W76-E099"
    },
    {
        "code": "KS/W76-E100",
        "name": "",
        "rarity": "",
        "bushi": "https://en.ws-tcg.com/cardlist/list/?cardno=KS/W76-E100"
    },
    {
        "code": "KS/W76-E101",
        "name": "",
        "rarity": "",
        "bushi": "https://en.ws-tcg.com/cardlist/list/?cardno=KS/W76-E101"
    },
    {
        "code": "KS/W76-E102",
        "name": "",
        "rarity": "",
        "bushi": "https://en.ws-tcg.com/cardlist/list/?cardno=KS/W76-E102"
    },
    {
        "code": "KS/W76-E103",
        "name": "",
        "rarity": "",
        "bushi": "https://en.ws-tcg.com/cardlist/list/?cardno=KS/W76-E103"
    },
    {
        "code": "KS/W76-E104",
        "name": "",
        "rarity": "",
        "bushi": "https://en.ws-tcg.com/cardlist/list/?cardno=KS/W76-E104"
    }
]